aissemble_encrypt/__init__.py
aissemble_encrypt/aes_cbc_encrypt.py
aissemble_encrypt/aes_cbc_encryption_strategy.py
aissemble_encrypt/aes_gcm_96_encrypt.py
aissemble_encrypt/aes_gcm_96_encryption_strategy.py
aissemble_encrypt/strategy_base.py
aissemble_encrypt/vault_config.py
aissemble_encrypt/vault_encrypt.py
aissemble_encrypt/vault_key_util.py
aissemble_encrypt/vault_local_encryption_strategy.py
aissemble_encrypt/vault_remote_encryption_strategy.py
aissemble_extensions_encryption_vault_python-1.12.1.dist-info/LICENSE
aissemble_extensions_encryption_vault_python-1.12.1.dist-info/METADATA
aissemble_extensions_encryption_vault_python-1.12.1.dist-info/WHEEL
aissemble_extensions_encryption_vault_python-1.12.1.dist-info/RECORD
