Metadata-Version: 2.1
Name: aissemble-extensions-encryption-vault-python
Version: 1.12.1
Summary: Vault data encryption classes (python)
Author: aiSSEMBLE Baseline Community
Author-email: aissemble@bah.com
Requires-Python: >=3.8
Classifier: Programming Language :: Python :: 3
Classifier: Programming Language :: Python :: 3.8
Classifier: Programming Language :: Python :: 3.9
Classifier: Programming Language :: Python :: 3.10
Classifier: Programming Language :: Python :: 3.11
Classifier: Programming Language :: Python :: 3.12
Classifier: Programming Language :: Python :: 3.13
Requires-Dist: cryptography (>=42.0.4)
Requires-Dist: hvac (>=1.0.0) ; python_version >= "3.8" and python_version < "4.0"
Requires-Dist: krausening (>=20)
Requires-Dist: urllib3 (>=1.26.18,<2.0.0)
